{
  "response": [
    {
      "datetime": 202208131043,
      "filename": "project-404-5.0-20220813-104358-SHINKA-cmi.zip",
      "id": "4eefa8f2c457ed0bfc81fe6beec3acef3f405a1d02a48b19de576579dcdc16b3",
      "romtype": "user",
      "size": 1858798776,
      "url": "https://github.com/P404-Devices/device_xiaomi_cmi/releases/download/5.0/project-404-5.0-20220813-104358-SHINKA-cmi.zip",
      "version": "5.0 (Shinka)",
      "links": {
        "xda": "",
        "supportGroup": "https://telegram.me/project_404",
        "deviceGroup": "https://telegram.me/mi10aosp"
      },
      "changes": [
          "Initial Official build of Android 12",
          "User build",
          "Selinux Enforced",
          "All 404 Goodness included!"
      ]
    }
  ]
}
